<?xml version="1.0" encoding="utf-8"?><toc><breadcrumbs><li><a href="4fecb639-f708-6876-03b0-2c80d5fafd8a.htm">Docs</a></li><li><a href="e2e2738e-c587-959b-5142-ebe8456f62fb.htm">iCloud.<wbr />Dav.<wbr />People Namespaces</a></li><li><a href="1b67d07d-3e18-8ff6-be51-ef43e05eceac.htm">iCloud.<wbr />Dav.<wbr />People.<wbr />Resources</a></li><li><a href="2fd06594-9b0a-dd90-c12e-b100d6ff60e4.htm">Identity<wbr />Card<wbr />Resource.<wbr />List<wbr />Request</a></li></breadcrumbs><tocItems><li><a id="10963569-0c9d-5d67-34e0-f9b7a367bd96" href="10963569-0c9d-5d67-34e0-f9b7a367bd96.htm">Constructor</a></li><li><a id="fe4b346f-90f5-6570-64cb-38dedc623585" class="has-submenu" href="fe4b346f-90f5-6570-64cb-38dedc623585.htm"><span data-tocFile="../toc/IDBMCD.xml" class="icon toggle" onclick="ToggleExpandCollapse(this); return false;"><i class="fa fa-angle-right"> </i></span>Properties</a><ul class="toc-menu is-hidden"> </ul></li><li><a id="b11e2a7b-7e73-ea60-7ca0-fb5575f2db93" class="has-submenu" href="b11e2a7b-7e73-ea60-7ca0-fb5575f2db93.htm"><span data-tocFile="../toc/IDCMCD.xml" class="icon toggle" onclick="ToggleExpandCollapse(this); return false;"><i class="fa fa-angle-right"> </i></span>Methods</a><ul class="toc-menu is-hidden"> </ul></li></tocItems></toc>